MANIFEST.in
README.md
requirements.txt
setup.py
zabier/__init__.py
zabier/cli.py
zabier/commands/__init__.py
zabier/zabbix/__init__.py
zabier/zabbix/action.py
zabier/zabbix/base.py
zabier/zabbix/constants.py
zabier/zabbix/host.py
zabier/zabbix/hostgroup.py
zabier/zabbix/maintenance.py
zabier/zabbix/template.py
zabier_cli.egg-info/PKG-INFO
zabier_cli.egg-info/SOURCES.txt
zabier_cli.egg-info/dependency_links.txt
zabier_cli.egg-info/entry_points.txt
zabier_cli.egg-info/requires.txt
zabier_cli.egg-info/top_level.txt