Metadata-Version: 2.1
Name: zabier-cli
Version: 0.2.0
Summary: A CLI tool to automate Zabbix configurations.
Home-page: https://github.com/serverworks/zabier-cli
Author: Masashi Terui
Author-email: terui@serverworks.co.jp
License: MIT License
Keywords: zabbix automation cli
Platform: UNKNOWN
Classifier: Development Status :: 4 - Beta
Classifier: Intended Audience :: System Administrators
Classifier: License :: OSI Approved :: MIT License
Classifier: Programming Language :: Python
Classifier: Programming Language :: Python :: 3.7
